{
  "product": "Eiam-developerapi",
  "version": "2022-02-25",
  "apiDoc": {
    "hasDoc": [
      "CreateOrganizationalUnit",
      "CreateUser",
      "ListOrganizationalUnits",
      "EnableUser",
      "DeleteUser",
      "GenerateDeviceCode",
      "RevokeToken",
      "GetOrganizationalUnit",
      "AddUserToOrganizationalUnits",
      "SetUserPrimaryOrganizationalUnit",
      "GetUserIdByEmail",
      "PatchOrganizationalUnit",
      "DeleteOrganizationalUnit",
      "UpdateUserPassword",
      "DisableUser",
      "GetUserIdByUserExternalId",
      "GetApplicationProvisioningScope",
      "ListUsers",
      "ListOrganizationalUnitParentIds",
      "GetUser",
      "RemoveUserFromOrganizationalUnits",
      "PatchUser",
      "GenerateToken",
      "GetUserInfo",
      "GetUserIdByPhoneNumber",
      "GetUserIdByUsername",
      "GetOrganizationalUnitIdByExternalId"
    ],
    "noDoc": []
  },
  "deprecated": [],
  "endpoints": {}
}