{
  "product": "Tablestore",
  "version": "2020-12-09",
  "apiDoc": {
    "hasDoc": [
      "CreateInstance",
      "DeleteInstancePolicy",
      "ChangeResourceGroup",
      "DeleteInstance",
      "CheckInstancePolicy",
      "DescribeRegions",
      "TagResources",
      "UntagResources",
      "ListInstances",
      "UpdateInstanceElasticVCUUpperLimit",
      "GetInstance",
      "ListTagResources",
      "UpdateInstancePolicy",
      "UpdateInstance"
    ],
    "noDoc": []
  },
  "deprecated": [],
  "endpoints": {}
}