{
  "product": "ComputeNestSupplier",
  "version": "2021-05-21",
  "apiDoc": {
    "hasDoc": [
      "AddServiceSharedAccounts",
      "ApproveServiceUsage",
      "ContinueDeployServiceInstance",
      "CreateArtifact",
      "CreateService",
      "CreateServiceInstance",
      "CreateServiceUsage",
      "DeleteArtifact",
      "DeleteService",
      "DeleteServiceInstances",
      "DeployServiceInstance",
      "GetArtifact",
      "GetArtifactRepositoryCredentials",
      "GetServiceEstimateCost",
      "GetUploadCredentials",
      "LaunchService",
      "ListAcrImageRepositories",
      "ListAcrImageTags",
      "ModifyServiceInstanceResources",
      "GetServiceInstance",
      "GetServiceTemplateParameterConstraints",
      "ListServiceUsages",
      "ListServiceInstances",
      "ListServices",
      "ListArtifacts",
      "ListArtifactVersions",
      "RemoveServiceSharedAccounts",
      "UpdateService",
      "PreLaunchService",
      "StartServiceInstance",
      "RejectServiceUsage",
      "ReleaseArtifact",
      "StopServiceInstance",
      "UpdateServiceInstanceSpec",
      "RegisterService",
      "UpdateArtifact",
      "RollbackServiceInstance",
      "UpgradeServiceInstance",
      "GetService",
      "ListServiceSharedAccounts",
      "PushMeteringData",
      "RestartServiceInstance",
      "UpdateServiceInstanceAttribute"
    ],
    "noDoc": []
  },
  "deprecated": [],
  "endpoints": {}
}