{
  "product": "ROS",
  "version": "2019-09-10",
  "apiDoc": {
    "hasDoc": [
      "CancelStackOperation",
      "CreateTemplate",
      "DeleteStackGroup",
      "DeleteTemplate",
      "ContinueCreateStack",
      "CreateChangeSet",
      "CreateStackGroup",
      "GetStackInstance",
      "GenerateTemplateByScratch",
      "ListStackResourceDrifts",
      "GetStackPolicy",
      "ListChangeSets",
      "GetStackGroup",
      "DetectStackResourceDrift",
      "ListStackGroupOperations",
      "ListStackResources",
      "ListStackGroupOperationResults",
      "ListTemplateScratches",
      "GetChangeSet",
      "GetTemplateEstimateCost",
      "ListResourceTypeVersions",
      "GetTemplateSummary",
      "GetStackResource",
      "ListResourceTypes",
      "ListResourceTypeRegistrations",
      "ListTagValues",
      "StopStackGroupOperation",
      "SetTemplatePermission",
      "UpdateTemplate",
      "SetDeletionProtection",
      "RegisterResourceType",
      "DeleteChangeSet",
      "DeregisterResourceType",
      "CreateStack",
      "DescribeRegions",
      "DetectStackGroupDrift",
      "DeleteStackInstances",
      "GetResourceTypeTemplate",
      "CancelUpdateStack",
      "GetStackGroupOperation",
      "GetTemplate",
      "GenerateTemplatePolicy",
      "DetectStackDrift",
      "DeleteStack",
      "CreateStackInstances",
      "DeleteTemplateScratch",
      "CreateTemplateScratch",
      "GetFeatureDetails",
      "ExecuteChangeSet",
      "GetResourceType",
      "GetStackDriftDetectionStatus",
      "GetTemplateParameterConstraints",
      "ListStackGroups",
      "SetResourceType",
      "UpdateStackGroup",
      "ListStacks",
      "ListTagKeys",
      "UpdateStackInstances",
      "ListTemplateVersions",
      "MoveResourceGroup",
      "ListStackOperationRisks",
      "ListStackEvents",
      "SetStackPolicy",
      "UpdateTemplateScratch",
      "ListTagResources",
      "GetStack",
      "UpdateStack",
      "GetTemplateScratch",
      "UntagResources",
      "ListTemplates",
      "SignalResource",
      "TagResources",
      "ValidateTemplate",
      "GetServiceProvisions",
      "UpdateStackTemplateByResources",
      "ListStackInstances",
      "PreviewStack"
    ],
    "noDoc": [
      "GetTemplateRecommendParameters"
    ]
  },
  "deprecated": [],
  "endpoints": {}
}