{
  "product": "Gwlb",
  "version": "2024-04-15",
  "apiDoc": {
    "hasDoc": [
      "AddServersToServerGroup",
      "CreateListener",
      "CreateLoadBalancer",
      "CreateServerGroup",
      "DeleteListener",
      "DeleteServerGroup",
      "ListTagResources",
      "RemoveServersFromServerGroup",
      "ListServerGroups",
      "TagResources",
      "UpdateLoadBalancerZones",
      "GetListenerAttribute",
      "DescribeRegions",
      "DeleteLoadBalancer",
      "DescribeZones",
      "GetListenerHealthStatus",
      "GetLoadBalancerAttribute",
      "ListListeners",
      "ListLoadBalancers",
      "UpdateLoadBalancerAttribute",
      "UntagResources",
      "MoveResourceGroup",
      "UpdateServerGroupAttribute",
      "ListServerGroupServers",
      "UpdateListenerAttribute"
    ],
    "noDoc": []
  },
  "deprecated": [],
  "endpoints": {}
}