{
  "product": "RocketMQ",
  "version": "2022-08-01",
  "apiDoc": {
    "hasDoc": [
      "GetInstance",
      "CreateTopic",
      "DeleteConsumerGroup",
      "CreateConsumerGroup",
      "GetConsumerGroup",
      "DeleteInstance",
      "UpdateInstance",
      "GetTopic",
      "CreateInstance",
      "ListTopics",
      "UpdateConsumerGroup",
      "UpdateTopic",
      "DeleteTopic",
      "ListInstances",
      "ListConsumerGroups"
    ],
    "noDoc": [
      "DeleteTraceQueryRecord",
      "GetUserMetrics",
      "DownloadMessage",
      "GetConsumerGroupLag",
      "ListMetricMeta",
      "ListTopicSubscriptions",
      "ExportInstanceResources",
      "GetUserTags",
      "GetInstanceAccount",
      "GetConsumerGroupSubscription",
      "GetMessageDetail",
      "ImportInstanceResources",
      "GetTraceClientHosts",
      "SubmitQueryTrace",
      "ListAlertRules",
      "ListTraceQueryRecords",
      "ResetConsumeOffset",
      "ListRegions",
      "GetTraceData",
      "GetConsumerStack",
      "ListConsumerConnections",
      "GetTraceQueryRecord",
      "ListMessages",
      "ListConsumerGroupSubscriptions",
      "VerifySendMessage",
      "ListTraceQueryResults",
      "ChangeResourceGroup",
      "VerifyConsumeMessage"
    ]
  },
  "deprecated": [],
  "endpoints": {}
}