{
  "product": "SWAS-OPEN",
  "version": "2020-06-01",
  "apiDoc": {
    "hasDoc": [
      "AddCustomImageShareAccount",
      "AllocatePublicConnection",
      "ApplyFirewallTemplate",
      "AttachKeyPair",
      "CreateCommand",
      "CreateCustomImage",
      "CreateFirewallTemplate",
      "CreateInstanceKeyPair",
      "CreateSnapshot",
      "DeleteCustomImage",
      "DeleteFirewallRule",
      "DescribeCloudAssistantStatus",
      "DescribeDatabaseInstances",
      "DescribeFirewallTemplateRulesApplyResult",
      "DescribeMonitorData",
      "ListTagResources",
      "LoginInstance",
      "StopDatabaseInstance",
      "ModifyInstanceVncPassword",
      "EnableFirewallRule",
      "DeleteSnapshots",
      "ImportKeyPair",
      "DeleteFirewallTemplates",
      "InstallCloudAssistant",
      "ListFirewallRules",
      "ListCustomImages",
      "ListImages",
      "DescribeInstanceKeyPair",
      "CreateFirewallRules",
      "CreateInstances",
      "CreateKeyPair",
      "DeleteInstanceKeyPair",
      "DescribeCommands",
      "DescribeInstanceVncUrl",
      "DeleteFirewallRules",
      "DescribeCloudAssistantAttributes",
      "CreateFirewallRule",
      "DescribeFirewallTemplateApplyResults",
      "DescribeDatabaseErrorLogs",
      "DescribeCloudMonitorAgentStatuses",
      "DescribeInvocationResult",
      "DescribeFirewallTemplates",
      "DeleteKeyPairs",
      "DeleteFirewallTemplateRules",
      "DetachKeyPair",
      "DisableFirewallRule",
      "DescribeInstancePasswordsSetting",
      "RemoveCustomImageShareAccount",
      "StartDatabaseInstance",
      "RebootInstance",
      "RebootInstances",
      "ResetDisk",
      "StopInstances",
      "StartInstance",
      "UpdateSnapshotAttribute",
      "StartTerminalSession",
      "ModifyDatabaseInstanceDescription",
      "RunCommand",
      "CreateFirewallTemplateRules",
      "ListDisks",
      "StartInstances",
      "ListInstancePlansModification",
      "ListCustomImageShareAccounts",
      "ListInstanceStatus",
      "DescribeDatabaseSlowLogRecords",
      "ListKeyPairs",
      "ListInstancesTrafficPackages",
      "DescribeDatabaseInstanceParameters",
      "DescribeSecurityAgentStatus",
      "ListSnapshots",
      "ModifyFirewallTemplate",
      "UpdateCommandAttribute",
      "UploadInstanceKeyPair",
      "DeleteCommand",
      "RenewInstance",
      "TagResources",
      "RestartDatabaseInstance",
      "ListRegions",
      "DescribeCommandInvocations",
      "ModifyDatabaseInstanceParameter",
      "UpgradeInstance",
      "StopInstance",
      "DeleteSnapshot",
      "InvokeCommand",
      "ListPlans",
      "DeleteCustomImages",
      "UpdateInstanceAttribute",
      "DescribeInvocations",
      "ResetDatabaseAccountPassword",
      "ListInstances",
      "ModifyImageShareStatus",
      "ResetSystem",
      "UntagResources",
      "DescribeDatabaseInstanceMetricData",
      "ModifyFirewallRule",
      "ReleasePublicConnection",
      "InstallCloudMonitorAgent",
      "UpdateDiskAttribute"
    ],
    "noDoc": []
  },
  "deprecated": [],
  "endpoints": {}
}