{
  "product": "PaiRecService",
  "version": "2022-12-13",
  "apiDoc": {
    "hasDoc": [
      "ApplyEngineConfig",
      "BackflowFeatureConsistencyCheckJobData",
      "CheckInstanceResources",
      "CloneEngineConfig",
      "CloneExperiment",
      "CloneExperimentGroup",
      "CloneFeatureConsistencyCheckJobConfig",
      "CloneLaboratory",
      "CreateABMetric",
      "CreateABMetricGroup",
      "CreateCalculationJobs",
      "CreateCrowd",
      "CreateEngineConfig",
      "CreateExperiment",
      "CreateExperimentGroup",
      "CreateFeatureConsistencyCheckJob",
      "CreateInstanceResource",
      "CreateFeatureConsistencyCheckJobConfig",
      "CreateLaboratory",
      "CreateLayer",
      "CreateParam",
      "CreateScene",
      "CreateSubCrowd",
      "CreateTableMeta",
      "CreateTrafficControlTask",
      "DeleteABMetricGroup",
      "DeleteABMetric",
      "DeleteCrowd",
      "DeleteEngineConfig",
      "DeleteExperiment",
      "DeleteExperimentGroup",
      "DeleteLaboratory",
      "DeleteInstanceResource",
      "DeleteLayer",
      "DeleteParam",
      "DeleteScene",
      "DeleteSubCrowd",
      "DeleteTableMeta",
      "GetABMetric",
      "GetABMetricGroup",
      "GetCalculationJob",
      "GetEngineConfig",
      "GetExperiment",
      "GetExperimentGroup",
      "GetFeatureConsistencyCheckJob",
      "GetFeatureConsistencyCheckJobConfig",
      "GetInstance",
      "GetInstanceResource",
      "GetInstanceResourceTable",
      "GetLaboratory",
      "GetLayer",
      "GetScene",
      "GetSubCrowd",
      "GetTableMeta",
      "ListABMetricGroups",
      "ListABMetrics",
      "ListCalculationJobs",
      "ListCrowdUsers",
      "ListCrowds",
      "ListEngineConfigs",
      "ListExperimentGroups",
      "ListExperiments",
      "ListFeatureConsistencyCheckJobConfigs",
      "ListFeatureConsistencyCheckJobFeatureReports",
      "ListFeatureConsistencyCheckJobs",
      "ListFeatureConsistencyCheckJobScoreReports",
      "ListInstanceResources",
      "ListInstances",
      "ListLaboratories",
      "ListParams",
      "ListLayers",
      "ListScenes",
      "ListSubCrowds",
      "ListTableMetas",
      "OfflineExperiment",
      "OfflineExperimentGroup",
      "OfflineLaboratory",
      "OnlineExperiment",
      "OnlineExperimentGroup",
      "OnlineLaboratory",
      "PushAllExperiment",
      "ReportABMetricGroup",
      "SyncFeatureConsistencyCheckJobReplayLog",
      "UpdateInstanceResource",
      "UpdateABMetric",
      "UpdateEngineConfig",
      "UpdateLaboratory",
      "TerminateFeatureConsistencyCheckJob",
      "UpdateScene",
      "UpdateLayer",
      "UpdateABMetricGroup",
      "UpdateFeatureConsistencyCheckJobConfig",
      "UpdateParam",
      "UpdateExperiment",
      "UpdateCrowd",
      "UpdateTableMeta",
      "UpdateExperimentGroup"
    ],
    "noDoc": [
      "CheckTrafficControlTaskExpression",
      "CloneTrafficControlTask",
      "CompareSampleConsistencyJob",
      "CreateResourceRuleItem",
      "CreateResourceRule",
      "CreateSampleConsistencyJob",
      "CreateTrafficControlTarget",
      "DebugResourceRule",
      "DeleteResourceRule",
      "DeleteResourceRuleItem",
      "DeleteSampleConsistencyJob",
      "DeleteTrafficControlTarget",
      "DeleteTrafficControlTask",
      "GenerateTrafficControlTaskCode",
      "GenerateTrafficControlTaskConfig",
      "GetResourceRule",
      "GetSampleConsistencyJob",
      "GetTrafficControlTask",
      "GetTrafficControlTarget",
      "GetTrafficControlTaskTraffic",
      "ListResourceRules",
      "ListSampleConsistencyJobs",
      "ListTrafficControlTargetTrafficHistory",
      "ListTrafficControlTasks",
      "QuerySampleConsistencyJobDifference",
      "QueryTrafficControlTargetItemReportDetail",
      "ReleaseTrafficControlTask",
      "ReportSampleConsistencyJob",
      "StartTrafficControlTarget",
      "StartTrafficControlTask",
      "StopSampleConsistencyJob",
      "SplitTrafficControlTarget",
      "StopTrafficControlTask",
      "StopTrafficControlTarget",
      "UpdateTrafficControlTask",
      "PushResourceRule",
      "UpdateTrafficControlTarget",
      "UpdateResourceRuleItem",
      "UpdateResourceRule",
      "UploadRecommendationData",
      "UpdateTrafficControlTaskTraffic"
    ]
  },
  "deprecated": [],
  "endpoints": {}
}