{
  "product": "eds-aic",
  "version": "2023-09-30",
  "apiDoc": {
    "hasDoc": [
      "CreateKeyPair",
      "AuthorizeAndroidInstance",
      "DeleteKeyPairs",
      "CreateCustomImage",
      "DeleteAndroidInstanceGroup",
      "DetachKeyPair",
      "DescribeSpec",
      "DeletePolicyGroup",
      "DescribeAndroidInstances",
      "DescribeAndroidInstanceGroups",
      "RecoveryFile",
      "DescribeInvocations",
      "ListPolicyGroups",
      "StartAndroidInstance",
      "UpdateInstanceGroupImage",
      "AttachKeyPair",
      "CreatePolicyGroup",
      "BackupFile",
      "DeleteApps",
      "DeleteImages",
      "ModifyPolicyGroup",
      "DescribeKeyPairs",
      "FetchFile",
      "DescribeRegions",
      "ModifyAndroidInstanceGroup",
      "UninstallApp",
      "ResetAndroidInstancesInGroup",
      "ModifyApp",
      "UpgradeAndroidInstanceGroup",
      "CheckResourceStock",
      "SetAdbSecure",
      "ImportKeyPair",
      "ModifyAndroidInstance",
      "DowngradeAndroidInstanceGroup",
      "RenewAndroidInstanceGroups",
      "DescribeBackupFiles",
      "RunCommand",
      "SendFile",
      "UpdateCustomImageName",
      "ModifyKeyPairName",
      "InstallApp",
      "DistributeImage",
      "GetAdbSecure"
    ],
    "noDoc": []
  },
  "deprecated": [],
  "endpoints": {}
}