{
  "product": "serverless",
  "version": "2021-09-24",
  "apiDoc": {
    "hasDoc": [],
    "noDoc": [
      "CreateTask",
      "GetApplication",
      "DeletePipelineTemplate",
      "GetRelease",
      "GetPipeline",
      "GetEnvironment",
      "DeleteApplication",
      "GetPipelineTemplate",
      "PutTaskStatus",
      "DeleteTaskTemplate",
      "ListEnvironmentRevisions",
      "StartPipeline",
      "ListEnvironments",
      "GetTemplate",
      "ListPipelines",
      "ListTemplateRevisions",
      "ListApplications",
      "DeleteEnvironment",
      "GetService",
      "CreateRelease",
      "CreatePipeline",
      "ListServices",
      "ListTemplates",
      "PutService",
      "CancelTask",
      "PutTaskTemplate",
      "PutTemplate",
      "RetryTask",
      "ListServiceRevisions",
      "StartTask",
      "UpdateApplication",
      "CreateApplication",
      "ListTaskTemplates",
      "ListPipelineTemplates",
      "GetTask",
      "DeleteTemplate",
      "ListTasks",
      "PutEnvironment",
      "CreatePipelineTemplate",
      "ResumeTask",
      "PutPipelineTemplate",
      "GetTaskTemplate",
      "PutPipelineStatus",
      "CreateTaskTemplate"
    ]
  },
  "deprecated": [],
  "endpoints": {}
}