{
  "product": "hitsdb",
  "version": "2020-06-15",
  "apiDoc": {
    "hasDoc": [
      "ChangeResourceGroup",
      "CreateLindormInstance",
      "CreateLindormV2Instance",
      "DescribeRegions",
      "GetInstanceIpWhiteList",
      "GetInstanceSummary",
      "GetLindormFsUsedDetail",
      "GetLindormInstance",
      "GetLindormInstanceEngineList",
      "GetLindormInstanceList",
      "GetLindormV2InstanceDetails",
      "GetLindormV2StorageUsage",
      "ModifyInstancePayType",
      "SwitchLSQLV3MySQLService",
      "ListTagResources",
      "UntagResources",
      "ReleaseLindormInstance",
      "RenewLindormInstance",
      "ReleaseLindormV2Instance",
      "UpdateLindormInstanceAttribute",
      "TagResources",
      "UpdateInstanceIpWhiteList",
      "UpgradeLindormInstance",
      "UpdateLindormV2Instance",
      "UpdateLindormV2WhiteIpList"
    ],
    "noDoc": [
      "CheckLdpsColumnarIndexStatus",
      "CreateAutoScalingConfig",
      "CreateAutoScalingRule",
      "CreateLdpsComputeGroup",
      "DeleteAutoScalingConfig",
      "DeleteAutoScalingRule",
      "DeleteCustomResource",
      "DeleteLdpsComputeGroup",
      "DeployLdpsSemiManagedComponent",
      "GetAutoScalingConfig",
      "GetAutoScalingRule",
      "GetClientSourceIp",
      "GetEngineDefaultAuth",
      "GetInstanceSecurityGroups",
      "GetLdpsComputeGroup",
      "GetLdpsNamespacedQuota",
      "GetLdpsResourceCost",
      "GetLindormEngineConfig",
      "GetLindormV2Instance",
      "GetLindormV2InstanceEngineList",
      "GetLindormV2InstanceForTerraform",
      "GetLindormV2InstanceSecurityGroups",
      "ListAutoScalingConfigs",
      "ListAutoScalingRecords",
      "ListAutoScalingRules",
      "OpenLdpsColumnarIndex",
      "ModifyLindormV2WhiteIpList",
      "OpenComputeEngine",
      "RestartLdpsComputeGroup",
      "OpenComputePreCheck",
      "ModifyLindormV2Instance",
      "ModifyAutoScalingConfig",
      "ModifyLindormV2InstanceSecurityGroups",
      "SetDefaultOlapComputeGroup",
      "UpdateInstanceSecurityGroups",
      "UpdateLdpsComputeGroup",
      "UpgradeLindormV2StreamEngine",
      "ListLdpsComputeGroups",
      "GetLindormV2StreamEngineInfo",
      "MigrateSingleZoneToMultiZone",
      "ModifyAutoScalingRule",
      "UpdateLindormV2InstanceParameter"
    ]
  },
  "deprecated": [],
  "endpoints": {}
}