{
  "product": "BDRC",
  "version": "2023-08-08",
  "apiDoc": {
    "hasDoc": [
      "DescribeTask",
      "UpdateResources",
      "DescribeProducts",
      "DescribeResources",
      "DescribeCheckDetails",
      "CheckRules",
      "DisableCheckResource",
      "CloseBdrcService",
      "EnableCheckResource",
      "GetBdrcService",
      "EnableCheckProduct",
      "DescribeTasks",
      "DescribeRules",
      "DescribeTopRiskyResources",
      "DisableCheckProduct",
      "OpenBdrcService"
    ],
    "noDoc": []
  },
  "deprecated": [],
  "endpoints": {}
}