{
  "product": "PAIABTest",
  "version": "2024-01-19",
  "apiDoc": {
    "hasDoc": [],
    "noDoc": [
      "CheckLayer",
      "CreateCrowd",
      "CreateDomain",
      "CreateExperiment",
      "CreateLayer",
      "CreateMetric",
      "CreateMetricGroup",
      "CreateProject",
      "CreateTableMeta",
      "DeleteDomain",
      "DeleteFeature",
      "DeleteMetric",
      "DeleteProject",
      "GetExperimentVersion",
      "GetFeature",
      "GetLayer",
      "GetMetric",
      "GetMetricGroup",
      "GetProject",
      "GetTableMeta",
      "ListDomains",
      "ListExperimentVersions",
      "ListExperiments",
      "ListFeatures",
      "ListMetrics",
      "ListLayers",
      "ListTableMetas",
      "StartExperiment",
      "CreateFeature",
      "UpdateCrowd",
      "PushAllExperimentVersion",
      "ListMetricGroups",
      "DeleteTableMeta",
      "DeleteCrowd",
      "DeleteLayer",
      "GetExperiment",
      "ListCrowds",
      "GetCrowd",
      "CreateExperimentVersion",
      "DeleteExperiment",
      "UpdateExperiment",
      "UpdateTableMeta",
      "UpdateMetric",
      "UpdateDomain",
      "UpdateProject",
      "DeleteMetricGroup",
      "UpdateMetricGroup",
      "UpdateLayer",
      "GetDomain",
      "StopExperiment",
      "UpdateExperimentVersion",
      "ListProjects",
      "UpdateFeature",
      "DeleteExperimentVersion"
    ]
  },
  "deprecated": [],
  "endpoints": {}
}