{
  "product": "PaiFeatureStore",
  "version": "2023-06-21",
  "apiDoc": {
    "hasDoc": [
      "DeleteFeatureEntity",
      "CreateModelFeature",
      "GetFeatureEntity",
      "CreateServiceIdentityRole",
      "CreateLabelTable",
      "CreateInstance",
      "ExportModelFeatureTrainingSetTable",
      "GetTask",
      "GetInstance",
      "GetModelFeature",
      "CheckInstanceDatasource",
      "CreateDatasource",
      "DeleteLLMConfig",
      "DeleteDatasource",
      "GetLabelTable",
      "GetDatasource",
      "ListDatasourceTables",
      "GetProjectFeatureEntity",
      "GetModelFeatureFGFeature",
      "ListDatasourceFeatureViews",
      "ListDatasources",
      "ListFeatureViewRelationships",
      "ListFeatureEntities",
      "PublishFeatureViewTable",
      "DeleteFeatureView",
      "ListFeatureViews",
      "ListInstances",
      "GetModelFeatureFGInfo",
      "CreateFeatureEntity",
      "CreateLLMConfig",
      "UpdateLabelTable",
      "UpdateDatasource",
      "UpdateLLMConfig",
      "ListLabelTables",
      "StopTask",
      "ListFeatureViewFieldRelationships",
      "GetDatasourceTable",
      "ListTasks",
      "UpdateProject",
      "ListProjects",
      "ListProjectFeatureViews",
      "ListModelFeatures",
      "CreateFeatureView",
      "GetFeatureView",
      "GetLLMConfig",
      "DeleteModelFeature",
      "GetProject",
      "CheckModelFeatureFGFeature",
      "DeleteProject",
      "DeleteLabelTable",
      "UpdateModelFeature",
      "ListModelFeatureAvailableFeatures",
      "ListFeatureViewOnlineFeatures",
      "ListTaskLogs",
      "CreateProject",
      "ListLLMConfigs",
      "GetServiceIdentityRole",
      "WriteFeatureViewTable",
      "ListProjectFeatures",
      "UpdateModelFeatureFGFeature"
    ],
    "noDoc": []
  },
  "deprecated": [],
  "endpoints": {}
}